cgcnn2/__init__.py
cgcnn2/asset/atom_init.json
cgcnn2/cli/__init__.py
cgcnn2/cli/cgcnn_ft.py
cgcnn2/cli/cgcnn_init.py
cgcnn2/cli/cgcnn_pr.py
cgcnn2/cli/cgcnn_tr.py
cgcnn2/data.py
cgcnn2/model.py
cgcnn2/pretrained_models/README.md
cgcnn2/pretrained_models/__init__.py
cgcnn2/pretrained_models/band-gap.pth.tar
cgcnn2/pretrained_models/bulk-moduli.pth.tar
cgcnn2/pretrained_models/efermi.pth.tar
cgcnn2/pretrained_models/final-energy-per-atom.pth.tar
cgcnn2/pretrained_models/formation-energy-per-atom.pth.tar
cgcnn2/pretrained_models/poisson-ratio.pth.tar
cgcnn2/pretrained_models/semi-metal-classification.pth.tar
cgcnn2/pretrained_models/shear-moduli.pth.tar
cgcnn2/utils.py
cgcnn2-0.5.3.dist-info/WHEEL
cgcnn2-0.5.3.dist-info/entry_points.txt
cgcnn2-0.5.3.dist-info/METADATA
cgcnn2-0.5.3.dist-info/RECORD
