Metadata-Version: 2.3
Name: cgcnn2
Version: 0.5.3
Summary: Reproduction of Crystal Graph Convolutional Neural Networks
Keywords: computational-materials,fine-tuning,graph-model,python
Author: Jiacheng Wang
Author-email: Jiacheng Wang <jiachengwang@umass.edu>
License: MIT
Classifier: Development Status :: 1 - Planning
Classifier: Intended Audience :: Science/Research
Classifier: Operating System :: OS Independent
Classifier: Programming Language :: Python :: 3 :: Only
Classifier: Programming Language :: Python :: 3.11
Classifier: Programming Language :: Python :: 3.12
Classifier: Programming Language :: Python :: 3.13
Requires-Dist: matplotlib
Requires-Dist: numpy
Requires-Dist: pandas
Requires-Dist: pymatgen>=2025.1.9
Requires-Dist: torch>=2.2
Maintainer: Jiacheng Wang
Maintainer-email: Jiacheng Wang <jiachengwang@umass.edu>
Requires-Python: >=3.11, <3.14
Project-URL: homepage, https://github.com/jcwang-dev/cgcnn2/
Project-URL: repository, https://github.com/jcwang-dev/cgcnn2/
